{
    "4669d00c8621e9a0281e783c77782dd4": {
        "(3, 19)": {
            "WBF": [
                2840
            ], 
            "AM2L": [
                2758
            ], 
            "BM1F": [
                1541
            ], 
            "M1": [
                1604
            ], 
            "M2": [
                2479
            ], 
            "BM1L": [
                1615
            ], 
            "WBO": [
                2844, 
                2202, 
                1815, 
                2844, 
                1931, 
                253, 
                1351, 
                130, 
                469, 
                436, 
                358, 
                3129
            ], 
            "WBL": [
                2844
            ], 
            "AM2F": [
                1829
            ], 
            "M1_ADJ": [
                1
            ]
        }, 
        "location1": [
            3
        ], 
        "location2": [
            19
        ], 
        "sentence": "the lcd is larger than the previous model , the nx , and has a bright blue backlight which illuminates the screen more successfully than the nx 's green backlight did ."
    }, 
    "009a83596167fefb74ee4f99f3da73be": {
        "location1": [
            9
        ], 
        "location2": [
            12
        ], 
        "(9, 12)": {
            "WBF": [
                1927
            ], 
            "AM2L": [
                1541
            ], 
            "BM1F": [
                130
            ], 
            "M1": [
                1604
            ], 
            "M2": [
                2479
            ], 
            "BM1L": [
                3158
            ], 
            "WBO": [
                359
            ], 
            "WBL": [
                359
            ], 
            "AM2F": [
                3129
            ], 
            "M1_ADJ": [
                1
            ]
        }, 
        "sentence": "the xtra improves upon the zen nx with a larger , now-blue backlit screen , which is infinitely better ."
    }
}