{
    "ff02148f541cf5f18c7b9c51fb6d96d1": {
        "(5, 6)": {
            "AM2L": [
                2859
            ], 
            "BM1F": [
                1951
            ], 
            "M1": [
                1033
            ], 
            "M2": [
                1264
            ], 
            "BM1L": [
                1595
            ], 
            "WBNULL": [
                1
            ], 
            "AM2F": [
                1967
            ], 
            "M1_ADJ": [
                1
            ]
        }, 
        "location1": [
            5
        ], 
        "location2": [
            6
        ], 
        "sentence": "i find the lack of entertaining game on this phone quite disturbing ."
    }
}