{
    "creative_organizer": "p", 
    "other_division": "p", 
    "sound_price": "p", 
    "great_software": "p", 
    "small_light": "p", 
    "notmad_reason": "p", 
    "creative_music": "p", 
    "little_construction": "p", 
    "creative_year": "p", 
    "additional_disk": "p", 
    "enough_volume": "p", 
    "larger_headphone": "p", 
    "superior_sound": "p", 
    "audio_file": "p", 
    "good_output": "p", 
    "3rd-party_earphone": "p", 
    "much_material": "p", 
    "other_way": "p", 
    "ive_em": "p", 
    "many_way": "p", 
    "cumbersome_button": "p", 
    "good_buy": "p", 
    "huge_space": "p", 
    "big_money-saver": "p", 
    "same-sounding_name": "p", 
    "other_device": "p", 
    "spare_battery": "p", 
    "front_plate": "p", 
    "other_player": "p", 
    "disappointing_product": "p", 
    "enclosed_software": "p", 
    "other_control": "p", 
    "cheaper_price": "p", 
    "enough_song": "p", 
    "outstanding_zen": "p", 
    "huge_difference": "p", 
    "new_ipod": "p", 
    "decent_size": "p", 
    "previous_model": "p", 
    "creative_issue": "p", 
    "nice_button": "p", 
    "replaceable_battery": "p", 
    "creative_software": "p", 
    "large_number": "p", 
    "good_interface": "p", 
    "different_thing": "p", 
    "best_bang": "p", 
    "real_complaint": "p", 
    "major_advantage": "p", 
    "nice_pair": "p", 
    "first_day": "p", 
    "favorite_cd": "p", 
    "previous_player": "p", 
    "other_people": "p", 
    "good_product": "p", 
    "convenient_device": "p", 
    "different_type": "p", 
    "great_advantage": "p", 
    "cool_screen": "p", 
    "aweful_gripe": "p", 
    "only_gripe": "p", 
    "green_backlight": "p", 
    "price-wise_zen": "p", 
    "entire_collection": "p", 
    "awesome_thing": "p", 
    "terrific_sound": "p", 
    "sound_output": "p", 
    "high_screen": "p", 
    "battery-powered_appliance": "p", 
    "other_company": "p", 
    "large_file": "p", 
    "good_option": "p", 
    "best_part": "p", 
    "many_player": "p", 
    "creative_mediasource": "p", 
    "particular_s": "p", 
    "blue-screen_display": "p", 
    "creative_lab": "p", 
    "big_zero": "p", 
    "greatest_album": "p", 
    "replacable_battery": "p", 
    "portable_speaker": "p", 
    "chic_look": "p", 
    "nice_unit": "p", 
    "bulky_support": "p", 
    "difficult_navigation": "p", 
    "lower_quality": "p", 
    "overall_disappointment": "p", 
    "big_flaw": "p", 
    "serious_nothing": "p", 
    "40gb_ipod": "p", 
    "large_head-phones": "p", 
    "larger_size": "p", 
    "larger_screen": "p", 
    "next_gap": "p", 
    "better_system": "p", 
    "different_variation": "p", 
    "awesome_collection": "p", 
    "readable_screen": "p", 
    "new_software": "p", 
    "other_plus": "p", 
    "audio_aspect": "p", 
    "external_receiver": "p", 
    "great_product": "p", 
    "sound_presets": "p", 
    "peripheral_business": "p", 
    "doesnt_work": "p", 
    "aweful_earphone": "p", 
    "large_collection": "p", 
    "superior_format": "p", 
    "sound_makes": "p", 
    "mp3_player": "p", 
    "favorite_thing": "p", 
    "most_user": "p", 
    "exceptional_sound": "p", 
    "other_thing": "p", 
    "exceptional_quality": "p", 
    "good_becuase": "p", 
    "navigational_system": "p", 
    "sturdier_button": "p", 
    "different_player": "p", 
    "sound_feature": "p", 
    "flimsy_control": "p", 
    "large-capacity_player": "p", 
    "easy_navigation": "p", 
    "beautiful_screen": "p", 
    "nice_extra": "p", 
    "other_product": "p", 
    "low_price": "p", 
    "only_reason": "p", 
    "sound_rate": "p", 
    "small_fortune": "p", 
    "big_deal": "p", 
    "excellent_sound": "p", 
    "poor_design": "p", 
    "only_thing": "p", 
    "biggest_advantage": "p", 
    "main_problem": "p", 
    "painless_process": "p", 
    "playback_quality": "p", 
    "great_value": "p", 
    "simple_button": "p", 
    "sound_battery": "p", 
    "only_downside": "p", 
    "actual_drive": "p", 
    "friendly_user": "p", 
    "lousy_warranty": "p", 
    "many_option": "p", 
    "good_headphone": "p", 
    "cheesiest_construction": "p", 
    "large_screen": "p", 
    "great_deal": "p", 
    "40gb_monster": "p", 
    "back-lit_screen": "p", 
    "lowest_ipod": "p", 
    "little_pressure": "p", 
    "sound_level": "p", 
    "unbeatable_price": "p", 
    "blue_backlight": "p", 
    "friendly_imo": "p", 
    "better_value": "p", 
    "sound_people": "p", 
    "new_nomad": "p", 
    "hard_disk": "p", 
    "decent_construction": "p", 
    "bright_backlight": "p", 
    "ho-hum_thing": "p", 
    "good_protection": "p", 
    "portable_radio": "p", 
    "annoying_display": "p", 
    "front_cover": "p", 
    "sound_software": "p", 
    "excellent_player": "p", 
    "good_service": "p", 
    "most_player": "p", 
    "crappy_headphone": "p", 
    "most_mp3": "p", 
    "sound_size": "p", 
    "other_vendor": "p", 
    "doesnt_look": "p", 
    "blue_light": "p", 
    "new_player": "p", 
    "sound_product": "p", 
    "clear_light": "p", 
    "sound_xtra": "p", 
    "awesome_recharge": "p", 
    "good_achievement": "p", 
    "big_hassle": "p", 
    "real_plus": "p", 
    "good_player": "p", 
    "poor_support": "p", 
    "whole_bunch": "p", 
    "huge_auditorium": "p", 
    "great_unit": "p", 
    "flimsy_wheel": "p", 
    "powerful_battery": "p", 
    "most_reviewer": "p", 
    "third_company": "p", 
    "external_speaker": "p", 
    "creative_number": "p", 
    "better_player": "p", 
    "audio_sync": "p", 
    "slick-looking_design": "p", 
    "different_presets": "p", 
    "overpriced_ipod": "p", 
    "good_sound": "p", 
    "other_problem": "p", 
    "nice_screen": "p", 
    "good_case": "p", 
    "nice_job": "p", 
    "blue_screen": "p", 
    "excellent_feature": "p", 
    "ideal_player": "p", 
    "best_deal": "p", 
    "most_people": "p", 
    "big_backlight": "p", 
    "lower_price": "p", 
    "hard-drive_player": "p", 
    "fine_product": "p", 
    "superior_piece": "p", 
    "normal_player": "p", 
    "live_album": "p", 
    "good_accessory": "p", 
    "asthetic_player": "p", 
    "other_word": "p", 
    "removable_battery": "p", 
    "good_thing": "p", 
    "small_environment": "p", 
    "great_quality": "p", 
    "ideal_purchase": "p", 
    "low_end": "p", 
    "small_collection": "p", 
    "automatic_sync": "p", 
    "frustrating_way": "p", 
    "quick_sync": "p", 
    "great_battery": "p", 
    "nice_bonus": "p", 
    "creative_xtra": "p", 
    "defective_system": "p", 
    "real_pair": "p", 
    "different_class": "p", 
    "light_environment": "p", 
    "resistant_case": "p", 
    "sound_fact": "p", 
    "lousy_day": "p", 
    "creative_company": "p", 
    "great_misfortune": "p", 
    "doesnt_case": "p", 
    "perfect_care": "p", 
    "external_noise": "p", 
    "easy_screen": "p", 
    "third_software": "p", 
    "great_player": "p", 
    "nice_feel": "p", 
    "other_appliance": "p", 
    "40gb_drive": "p", 
    "short_warranty": "p", 
    "better_control": "p", 
    "audio_interference": "p", 
    "hard_plastic": "p", 
    "surprising_business": "p", 
    "dense_feel": "p", 
    "dynamic_playlist": "p", 
    "better_xtra": "p", 
    "interesting_feature": "p", 
    "shoddy_construction": "p", 
    "main_computer": "p", 
    "single_problem": "p", 
    "little_piece": "p", 
    "batterly_life": "p", 
    "best_player": "p", 
    "cheap_battery": "p", 
    "overall_player": "p", 
    "huge_capacity": "p", 
    "front_panel": "p", 
    "notmad_software": "p", 
    "portable_player": "p", 
    "main_requirement": "p", 
    "good_quality": "p", 
    "neccessary_lil": "p", 
    "easy_capacity": "p", 
    "creative_advantage": "p", 
    "dimished_quality": "p", 
    "good_deal": "p", 
    "best_buy": "p", 
    "changable_battery": "p", 
    "sound_life": "p", 
    "much_piece": "p", 
    "well-placed_control": "p", 
    "creative_player": "p", 
    "regular_pair": "p", 
    "more_problem": "p", 
    "creative_call": "p", 
    "next_month": "p", 
    "cumbersome_work-around": "p", 
    "great_sound": "p", 
    "major_problem": "p", 
    "ho-hum_software": "p", 
    "user-replaceable_battery": "p", 
    "right_control": "p", 
    "little_bit": "p", 
    "cheap_construction": "p", 
    "tiny_piece": "p", 
    "superior_quality": "p", 
    "creative_people": "p", 
    "creative_product": "p", 
    "consistent_feedback": "p", 
    "portable_drive": "p", 
    "other_mp3s": "p", 
    "audio_bookmark": "p", 
    "other_reviewer": "p", 
    "creative_feedback": "p", 
    "extraneous_noise": "p", 
    "small_device": "p", 
    "only_accessory": "p", 
    "back-up_device": "p", 
    "yoursound_quality": "p", 
    "good_sync": "p", 
    "great_makes": "p", 
    "audio_business": "p", 
    "relatively-intuitive_system": "p", 
    "sound_quality": "p", 
    "convenient_zen": "p", 
    "more_battery": "p", 
    "entire_process": "p", 
    "select_song": "p", 
    "various_button": "p", 
    "terrible_software": "p", 
    "good_xtra": "p", 
    "backlit_screen": "p", 
    "first_place": "p", 
    "other_review": "p", 
    "great_piece": "p", 
    "easier_system": "p", 
    "bulky_con": "p", 
    "advanced_feature": "p", 
    "big_storage": "p", 
    "new_headphone": "p", 
    "second_format": "p", 
    "other_button": "p", 
    "only_reservation": "p", 
    "other_sound": "p", 
    "hard_drive": "p", 
    "bigger_unit": "p", 
    "great_screen": "p", 
    "cool_one": "p", 
    "excellent_bookmark": "p", 
    "creative_support": "p", 
    "sound_screen": "p", 
    "good_software": "p", 
    "big_durability": "p", 
    "serious_flaw": "p", 
    "great_feature": "p", 
    "40gb_xtra": "p", 
    "protective_case": "p", 
    "mediocre_player": "p", 
    "new_battery": "p", 
    "simple_one": "p", 
    "different_deal": "p", 
    "large_player": "p", 
    "easier_software": "p", 
    "great_price": "p", 
    "sturdier_case": "p", 
    "good_price": "p", 
    "hard_copy": "p", 
    "useless_case": "p", 
    "many_people": "p", 
    "awesome_music": "p", 
    "sound_update": "p", 
    "60gb_nomad": "p", 
    "main_factor": "p", 
    "excellent_product": "p", 
    "extra_pressure": "p", 
    "outstanding_way": "p", 
    "doesnt_close": "p", 
    "different_headphone": "p", 
    "noticeable_gap": "p", 
    "inferior_system": "p", 
    "second_player": "p", 
    "now-blue_screen": "p", 
    "creative_sound": "p", 
    "other_tagging": "p", 
    "sound_ok": "p", 
    "simple_thing": "p", 
    "bigger_bit": "p", 
    "small_headphone": "p", 
    "remote_interface": "p"
}